LICENSE
MANIFEST.in
README.md
setup.cfg
setup.py
django_query_execfile.egg-info/PKG-INFO
django_query_execfile.egg-info/SOURCES.txt
django_query_execfile.egg-info/dependency_links.txt
django_query_execfile.egg-info/requires.txt
django_query_execfile.egg-info/top_level.txt
query_execfile/__init__.py
query_execfile/django_sql_execfile.py