Metadata-Version: 1.1
Name: django-query-execfile
Version: 0.5
Summary: A Django module for execute custom sql query in a .sql file
Home-page: https://github.com/tranvietanh1991/django-query-execfile
Author: V.Anh Tran
Author-email: tranvietanh1991@gmail.com
License: MIT
Download-URL: https://github.com/tranvietanh1991/django-query-execfile/archive/master.zip
Keywords: django,query,sql,execute,file
Platform: UNKNOWN
Classifier: Development Status :: 4 - Beta
Classifier: Environment :: Web Environment
Classifier: Framework :: Django
Classifier: Intended Audience :: Developers
Classifier: Intended Audience :: System Administrators
Classifier: License :: OSI Approved :: MIT License
Classifier: Operating System :: OS Independent
Classifier: Programming Language :: Python :: 2
Classifier: Topic :: Software Development :: Libraries :: Python Modules
